ovos_ocp_news_plugin/__init__.py
ovos_ocp_news_plugin/config.py
ovos_ocp_news_plugin/extractors.py
ovos_ocp_news_plugin/version.py
ovos_ocp_news_plugin-0.1.1.dist-info/LICENSE
ovos_ocp_news_plugin-0.1.1.dist-info/METADATA
ovos_ocp_news_plugin-0.1.1.dist-info/WHEEL
ovos_ocp_news_plugin-0.1.1.dist-info/entry_points.txt
ovos_ocp_news_plugin-0.1.1.dist-info/top_level.txt
ovos_ocp_news_plugin-0.1.1.dist-info/zip-safe
ovos_ocp_news_plugin-0.1.1.dist-info/RECORD
