Metadata-Version: 2.1
Name: ovos-ocp-news-plugin
Version: 0.1.1
Summary: OCP news feed stream extractor plugin
Home-page: https://github.com/OpenVoiceOS/ovos-ocp-news-plugin
Author: JarbasAi
Author-email: jarbasai@mailfence.com
License: Apache-2.0
Keywords: ovos ocp plugin
Platform: UNKNOWN
Requires-Dist: ovos-plugin-manager<2.0.0,>=0.0.1
Requires-Dist: ovos-ocp-rss-plugin<1.0.0,>=0.0.2
Requires-Dist: ovos-ocp-m3u-plugin<1.0.0,>=0.0.1
Requires-Dist: pytz
Requires-Dist: beautifulsoup4
